{
    "boxShadow": "{{appsmith.theme.boxShadow.appBoxShadow}}",
    "borderColor": "#E0DEDE",
    "isVisibleDownload": true,
    "iconSVG": "/static/media/icon.c4395b694ca4b5a84741345b057b6866.svg",
    "topRow": 41,
    "isSortable": true,
    "type": "TABLE_WIDGET_V2",
    "inlineEditingSaveOption": "ROW_LEVEL",
    "animateLoading": true,
    "dynamicBindingPathList": [
        {"key": "accentColor"},
        {"key": "borderRadius"},
        {"key": "boxShadow"},
        {"key": "tableData"},
        {"key": "primaryColumns.amount.computedValue"},
        {"key": "primaryColumns.payment_count.computedValue"},
        {"key": "primaryColumns.total_amount.computedValue"}
    ],
    "needsHeightForContent": true,
    "leftColumn": 2,
    "delimiter": ",",
    "defaultSelectedRowIndex": 0,
    "flexVerticalAlignment": "start",
    "accentColor": "{{appsmith.theme.colors.primaryColor}}",
    "onCanvasUI": {
        "focusBGCSSVar": "--on-canvas-ui-widget-focus",
        "disableParentSelection": false,
        "focusColorCSSVar": "--on-canvas-ui-widget-selection",
        "selectionBGCSSVar": "--on-canvas-ui-widget-selection",
        "selectionColorCSSVar": "--on-canvas-ui-widget-focus"
    },
    "isVisibleFilters": true,
    "isVisible": true,
    "enableClientSideSearch": true,
    "version": 2,
    "totalRecordsCount": 0,
    "tags": [
        "Suggested",
        "Display"
    ],
    "isLoading": false,
    "childStylesheet": {
        "button": {
            "boxShadow": "none",
            "borderRadius": "{{appsmith.theme.borderRadius.appBorderRadius}}",
            "buttonColor": "{{appsmith.theme.colors.primaryColor}}"
        },
        "iconButton": {
            "boxShadow": "none",
            "borderRadius": "{{appsmith.theme.borderRadius.appBorderRadius}}",
            "buttonColor": "{{appsmith.theme.colors.primaryColor}}"
        },
        "menuButton": {
            "boxShadow": "none",
            "borderRadius": "{{appsmith.theme.borderRadius.appBorderRadius}}",
            "menuColor": "{{appsmith.theme.colors.primaryColor}}"
        },
        "editActions": {
            "saveButtonColor": "{{appsmith.theme.colors.primaryColor}}",
            "saveBorderRadius": "{{appsmith.theme.borderRadius.appBorderRadius}}",
            "discardBorderRadius": "{{appsmith.theme.borderRadius.appBorderRadius}}",
            "discardButtonColor": "{{appsmith.theme.colors.primaryColor}}"
        }
    },
    "borderRadius": "{{appsmith.theme.borderRadius.appBorderRadius}}",
    "columnUpdatedAt": 1716294914232,
    "originalBottomRow": 72,
    "defaultSelectedRowIndices": [0],
    "needsErrorInfo": false,
    "mobileBottomRow": 69,
    "widgetName": "Table3",
    "defaultPageSize": 0,
    "columnOrder": [
        "amount",
        "payment_count",
        "total_amount"
    ],
    "dynamicPropertyPathList": [{"key": "tableData"}],
    "displayName": "Table",
    "bottomRow": 69,
    "columnWidthMap": {},
    "parentRowSpace": 10,
    "hideCard": false,
    "mobileRightColumn": 36,
    "parentColumnSpace": 9.234375,
    "dynamicTriggerPathList": [],
    "borderWidth": "1",
    "primaryColumns": {
        "payment_count": {
            "computedValue": "{{Table3.processedTableData.map((currentRow, currentIndex) => ( currentRow[\"payment_count\"]))}}",
            "isEditable": false,
            "notation": "standard",
            "alias": "payment_count",
            "enableSort": true,
            "isSaveVisible": true,
            "id": "payment_count",
            "isDisabled": false,
            "allowSameOptionsInNewRow": true,
            "validation": {},
            "isCellVisible": true,
            "isDerived": false,
            "textSize": "0.875rem",
            "allowCellWrapping": false,
            "index": 1,
            "isDiscardVisible": true,
            "isVisible": true,
            "label": "payment_count",
            "fontStyle": "",
            "textColor": "",
            "columnType": "number",
            "thousandSeparator": true,
            "horizontalAlignment": "LEFT",
            "isCellEditable": false,
            "decimals": 0,
            "width": 150,
            "enableFilter": true,
            "sticky": "",
            "originalId": "payment_count",
            "currencyCode": "USD",
            "cellBackground": "",
            "verticalAlignment": "CENTER"
        },
        "amount": {
            "computedValue": "{{Table3.processedTableData.map((currentRow, currentIndex) => ( currentRow[\"amount\"]))}}",
            "isEditable": false,
            "notation": "standard",
            "alias": "amount",
            "enableSort": true,
            "isSaveVisible": true,
            "id": "amount",
            "isDisabled": false,
            "allowSameOptionsInNewRow": true,
            "validation": {},
            "isCellVisible": true,
            "isDerived": false,
            "textSize": "0.875rem",
            "allowCellWrapping": false,
            "index": 0,
            "isDiscardVisible": true,
            "isVisible": true,
            "label": "amount",
            "fontStyle": "",
            "textColor": "",
            "columnType": "number",
            "thousandSeparator": true,
            "horizontalAlignment": "LEFT",
            "isCellEditable": false,
            "decimals": 0,
            "width": 150,
            "enableFilter": true,
            "sticky": "",
            "originalId": "amount",
            "currencyCode": "USD",
            "cellBackground": "",
            "verticalAlignment": "CENTER"
        },
        "total_amount": {
            "computedValue": "{{Table3.processedTableData.map((currentRow, currentIndex) => ( currentRow[\"total_amount\"]))}}",
            "isEditable": false,
            "notation": "standard",
            "alias": "total_amount",
            "enableSort": true,
            "isSaveVisible": true,
            "id": "total_amount",
            "isDisabled": false,
            "allowSameOptionsInNewRow": true,
            "validation": {},
            "isCellVisible": true,
            "isDerived": false,
            "textSize": "0.875rem",
            "allowCellWrapping": false,
            "index": 2,
            "isDiscardVisible": true,
            "isVisible": true,
            "label": "total_amount",
            "fontStyle": "",
            "textColor": "",
            "columnType": "number",
            "thousandSeparator": true,
            "horizontalAlignment": "LEFT",
            "isCellEditable": false,
            "decimals": 0,
            "width": 150,
            "enableFilter": true,
            "sticky": "",
            "originalId": "total_amount",
            "currencyCode": "USD",
            "cellBackground": "",
            "verticalAlignment": "CENTER"
        }
    },
    "key": "n2uhjos2rk",
    "canFreezeColumn": true,
    "isDeprecated": false,
    "rightColumn": 30,
    "textSize": "0.875rem",
    "thumbnailSVG": "https://appcdn.appsmith.com/static/media/thumbnail.d0492f06681daa69baf92b07d3829dfc.svg",
    "widgetId": "9gjpmidr62",
    "minWidth": 450,
    "tableData": "{{Query2.data}}",
    "label": "Data",
    "searchKey": "",
    "parentId": "0",
    "renderMode": "CANVAS",
    "mobileTopRow": 41,
    "horizontalAlignment": "LEFT",
    "isVisibleSearch": true,
    "responsiveBehavior": "fill",
    "originalTopRow": 44,
    "mobileLeftColumn": 2,
    "isVisiblePagination": true,
    "verticalAlignment": "CENTER"
}